tests/__init__.py
tests/cases.py
tests/server.py
tests/tests.py
tpb/__init__.py
tpb/constants.py
tpb/tpb.py
tpb/utils.py
tpb-1.3.6.dist-info/AUTHORS.md
tpb-1.3.6.dist-info/LICENSE
tpb-1.3.6.dist-info/METADATA
tpb-1.3.6.dist-info/WHEEL
tpb-1.3.6.dist-info/top_level.txt
tpb-1.3.6.dist-info/RECORD
