Metadata-Version: 2.1
Name: tpb
Version: 1.3.6
Summary: Unofficial Python API for ThePirateBay.
Home-page: https://github.com/pawamoy/TPB/
Author: Karan Goel
Author-email: karan@goel.im
License: MIT License
Platform: UNKNOWN
Classifier: Development Status :: 4 - Beta
Classifier: License :: OSI Approved :: MIT License
Classifier: Operating System :: POSIX
Classifier: Programming Language :: Python
Classifier: Programming Language :: Python :: 2
Classifier: Programming Language :: Python :: 2.7
Classifier: Programming Language :: Python :: 3
Classifier: Programming Language :: Python :: 3.2
Classifier: Programming Language :: Python :: 3.3
Classifier: Topic :: Internet :: WWW/HTTP :: Browsers
Classifier: Topic :: Internet :: WWW/HTTP :: Indexing/Search
Classifier: Topic :: Utilities
Requires-Dist: purl
Requires-Dist: dateutils
Requires-Dist: lxml
Requires-Dist: cssselect
Requires-Dist: requests
